neuralhash/__init__.py
neuralhash/cli.py
neuralhash/core.py
neuralhash/model.onnx
neuralhash/neuralhash_128x96_seed1.dat
neuralhash-0.1.2.dist-info/licenses/LICENSE
neuralhash-0.1.2.dist-info/METADATA
neuralhash-0.1.2.dist-info/WHEEL
neuralhash-0.1.2.dist-info/entry_points.txt
neuralhash-0.1.2.dist-info/top_level.txt
neuralhash-0.1.2.dist-info/RECORD
