Metadata-Version: 2.4
Name: neuralhash
Version: 0.1.2
Summary: Generates a hash from a reverse engineered Apple NeuralHash model
Author-email: Josh Terrill <josh@hacked.codes>
License: MIT
Project-URL: Homepage, https://github.com/joshterrill/python-neuralhash
Project-URL: Repository, https://github.com/joshterrill/python-neuralhash
Project-URL: Issues, https://github.com/joshterrill/python-neuralhash/issues
Requires-Python: >=3.8
License-File: LICENSE
Requires-Dist: onnxruntime
Requires-Dist: pillow
Requires-Dist: numpy
Dynamic: license-file
